hbpycounts/__init__.py
hbpycounts/hbpycounts.py
hbpycounts/plotting.py
hbpycounts-0.1.0.dist-info/LICENSE
hbpycounts-0.1.0.dist-info/METADATA
hbpycounts-0.1.0.dist-info/WHEEL
hbpycounts-0.1.0.dist-info/RECORD
