Metadata-Version: 2.1
Name: hbpycounts
Version: 0.1.0
Summary: A sample python package
License: MIT
Author: Hina Bandukwala
Requires-Python: >=3.12
Classifier: License :: OSI Approved :: MIT License
Classifier: Programming Language :: Python :: 3
Classifier: Programming Language :: Python :: 3.12
Requires-Dist: matplotlib (>=3.8.2)
